regexfilesearch/LICENSE
regexfilesearch/README.MD
regexfilesearch/__init__.py
regexfilesearch/requirements.txt
regexfilesearch/thirdparty.json
regexfilesearch-0.11.dist-info/LICENSE.rst
regexfilesearch-0.11.dist-info/METADATA
regexfilesearch-0.11.dist-info/WHEEL
regexfilesearch-0.11.dist-info/top_level.txt
regexfilesearch-0.11.dist-info/RECORD
